pdfuck/__init__.py
pdfuck-1.0.2.dist-info/LICENSE
pdfuck-1.0.2.dist-info/METADATA
pdfuck-1.0.2.dist-info/WHEEL
pdfuck-1.0.2.dist-info/entry_points.txt
pdfuck-1.0.2.dist-info/top_level.txt
pdfuck-1.0.2.dist-info/RECORD
