Metadata-Version: 2.1
Name: pdfuck
Version: 1.0.2
Summary: PDFuck: Remove the password of your PDF file
Home-page: https://github.com/mmdjiji/pdfuck
Author: JiJi <i@mmdjiji.com>
License: GPL-3.0
Classifier: Programming Language :: Python :: 3
License-File: LICENSE
Requires-Dist: pikepdf
